arckit/__init__.py
arckit/cli.py
arckit/data.py
arckit/importtool.py
arckit/vis.py
arckit/data/arc1.json
arckit/data/arcagi2_f3283f7.json
arckit/data/arcagi_aa922be.json
arckit/data/kaggle2024.json
arckit/data/kaggle2025_250808.json
arckit-1.0.1.dist-info/licenses/LICENSE
arckit-1.0.1.dist-info/METADATA
arckit-1.0.1.dist-info/WHEEL
arckit-1.0.1.dist-info/entry_points.txt
arckit-1.0.1.dist-info/top_level.txt
arckit-1.0.1.dist-info/RECORD
