Metadata-Version: 2.4
Name: arckit
Version: 1.0.1
Summary: Tools for working with the Abstraction & Reasoning Corpus (ARC-AGI)
Author-email: Mikel Bober-Irizar <mikel@mxbi.net>
License-Expression: Apache-2.0
Project-URL: Homepage, https://github.com/mxbi/arckit
Project-URL: Repository, https://github.com/mxbi/arckit
Project-URL: Issues, https://github.com/mxbi/arckit/issues
Keywords: arc,agi,reasoning,abstraction
Classifier: Development Status :: 5 - Production/Stable
Classifier: Programming Language :: Python :: 3
Classifier: Programming Language :: Python :: 3.8
Classifier: Programming Language :: Python :: 3.9
Classifier: Programming Language :: Python :: 3.10
Classifier: Programming Language :: Python :: 3.11
Classifier: Programming Language :: Python :: 3.12
Classifier: Programming Language :: Python :: 3.13
Classifier: Topic :: Scientific/Engineering :: Artificial Intelligence
Requires-Python: >=3.8
License-File: LICENSE
Requires-Dist: numpy
Requires-Dist: rich
Requires-Dist: drawsvg
Dynamic: license-file
